README.rst
setup.py
rmb2/__init__.py
rmb2/rmb.py
rmb2.egg-info/PKG-INFO
rmb2.egg-info/SOURCES.txt
rmb2.egg-info/dependency_links.txt
rmb2.egg-info/top_level.txt