Metadata-Version: 2.1
Name: rmb2
Version: 0.0.3.1
Summary: rmb is a Python RMB translation library
Author: PyDa5
Author-email: 1174446068@qq.com
